{
  "jobs": [
    {
      "title": "Construction Worker",
      "sector": "Construction",
      "demographics": "2%",
      "income": 280,
      "hours": 40,
      "image": "Construction.png",
      "disabled": false
    },
    {
      "title": "Teacher",
      "sector": "Education",
      "demographics": "Less than 1%",
      "income": 420,
      "hours": 51,
      "image": "Education.png",
      "disabled": true
    },
    {
      "title": "Restaurant Waiter",
      "sector": "Food and Beverages",
      "demographics": "11%",
      "income": 320,
      "hours": 56,
      "image": "Food.png",
      "disabled": false
    },
    {
      "title": "Nurse",
      "sector": "Health",
      "demographics": "Less than 1%",
      "income": 1800,
      "hours": 50,
      "image": "Health.png",
      "disabled": true
    },
    {
      "title": "Hotel Security Guard",
      "sector": "Non-specialized Personal Services",
      "demographics": "17%",
      "income": 320,
      "hours": 56,
      "image": "Guard.png",
      "disabled": false
    },
    {
      "title": "Factory Worker",
      "sector": "Manufacturing",
      "demographics": "5%",
      "income": 310,
      "hours": 48,
      "image": "Manufacturing.png",
      "disabled": false
    },
    {
      "title": "Supermarket Cashier",
      "sector": "Non-specialized Personal Services",
      "demographics": "10%",
      "income": 300,
      "hours": 60,
      "image": "Wholesale.png",
      "disabled": false
    },
    {
      "title": "Street Vendor",
      "sector": "Informal",
      "demographics": "42%",
      "income": 240,
      "hours": 56,
      "image": "Informal.png",
      "disabled": false
    }
  ]
}